spectrend/__init__.py
spectrend/_version.py
spectrend/spectrend.py
spectrend-0.0.1.dist-info/LICENSE
spectrend-0.0.1.dist-info/METADATA
spectrend-0.0.1.dist-info/WHEEL
spectrend-0.0.1.dist-info/top_level.txt
spectrend-0.0.1.dist-info/RECORD
